[
    {
        "code": "222003",
        "question": "প্লেটোর মতে, রাষ্ট্রের কোন শ্রেণির ব্যক্তিগত সম্পত্তি ও পারিবারিক জীবন থাকবে?",
        "answer": "রাষ্ট্রের অভিজাত শ্রেণির ব্যক্তিগত সম্পত্তি ও পারিবারিক জীবন থাকবে।",
        "year": "2nd",
        "exam_year": "2018",
        "sl": "ক",
        "section": "ক-বিভাগ",
        "id": "222003_2018_01_01",
        "type": "Board"
    },
    {
        "code": "222003",
        "question": "এরিস্টটলের মতে, উত্তম সরকার কোনটি?",
        "answer": "পলিটি।",
        "year": "2nd",
        "exam_year": "2018",
        "sl": "খ",
        "section": "ক-বিভাগ",
        "id": "222003_2018_01_02",
        "type": "Board"
    },
    {
        "code": "222003",
        "question": "“পাপীকে ভালোবাস ও পাপকে ঘৃণা কর” -উক্তিটি কার?",
        "answer": "অগাস্টিনের।",
        "year": "2nd",
        "exam_year": "2018",
        "sl": "গ",
        "section": "ক-বিভাগ",
        "id": "222003_2018_01_03",
        "type": "Board"
    },
    {
        "code": "222003",
        "question": "ভারত বর্ষের কোন সম্রাটের আমলে কৌটিল্য প্রধানমন্ত্রী ছিলেন?",
        "answer": "চন্দ্রগুপ্তের।",
        "year": "2nd",
        "exam_year": "2018",
        "sl": "ঘ",
        "section": "ক-বিভাগ",
        "id": "222003_2018_01_04",
        "type": "Board"
    },
    {
        "code": "222003",
        "question": "“Leviathan” -গ্রন্থটির লেখক কে?",
        "answer": "টমাস হবস।",
        "year": "2nd",
        "exam_year": "2018",
        "sl": "ঙ",
        "section": "ক-বিভাগ",
        "id": "222003_2018_01_05",
        "type": "Board"
    },
    {
        "code": "222003",
        "question": "কে সর্বপ্রথম ধর্ম ও নৈতিকতাকে রাজনীতি থেকে পৃথক করেছেন?",
        "answer": "ম্যাকিয়াভেলি।",
        "year": "2nd",
        "exam_year": "2018",
        "sl": "চ",
        "section": "ক-বিভাগ",
        "id": "222003_2018_01_06",
        "type": "Board"
    },
    {
        "code": "222003",
        "question": "আল-উমরান কী?",
        "answer": "ইবনে খালদুনের রচিত একটি গ্রন্থ। সংস্কৃতির বিজ্ঞানকে আরবিতে আল-উমরান বলা হয়।",
        "year": "2nd",
        "exam_year": "2018",
        "sl": "ছ",
        "section": "ক-বিভাগ",
        "id": "222003_2018_01_07",
        "type": "Board"
    },
    {
        "code": "222003",
        "question": "জন লকের বিখ্যাত গ্রন্থটির নাম কি?",
        "answer": "Two Treatises on Civil Government.",
        "year": "2nd",
        "exam_year": "2018",
        "sl": "জ",
        "section": "ক-বিভাগ",
        "id": "222003_2018_01_08",
        "type": "Board"
    },
    {
        "code": "222003",
        "question": "কৌটিল্যের আসল নাম কী?",
        "answer": "বিষ্ণুগুপ্ত।",
        "year": "2nd",
        "exam_year": "2018",
        "sl": "ঝ",
        "section": "ক-বিভাগ",
        "id": "222003_2018_01_09",
        "type": "Board"
    },
    {
        "code": "222003",
        "question": "একুইনাসের মতে, আইন কত প্রকার?",
        "answer": "৪ প্রকার। যথা- (ক) শাশ্বত আইন, (খ) প্রাকৃতিক আইন, (গ) ঐশ্বরিক আইন ও (ঘ) মানবিক আইন।",
        "year": "2nd",
        "exam_year": "2018",
        "sl": "ঞ",
        "section": "ক-বিভাগ",
        "id": "222003_2018_01_10",
        "type": "Board"
    },
    {
        "code": "222003",
        "question": "রুশোর মতে, বাস্তব ইচ্ছা কী?",
        "answer": "যে ব্যাক্তি তার স্বীয় স্বার্থকে যথার্থ স্বার্থ বলে মনে করে তাই বাস্তব ইচ্ছা।",
        "year": "2nd",
        "exam_year": "2018",
        "sl": "ট",
        "section": "ক-বিভাগ",
        "id": "222003_2018_01_11",
        "type": "Board"
    },
    {
        "code": "222003",
        "question": "একুইনাসের মতে, ক্রীতদাস কয় ধরনের?",
        "answer": "২ ধরনের। যথা- প্রকৃতিগত দাস ও আইনগত দাস।",
        "year": "2nd",
        "exam_year": "2018",
        "sl": "ঠ",
        "section": "ক-বিভাগ",
        "id": "222003_2018_01_12",
        "type": "Board"
    },
    {
        "code": "222003",
        "question": "প্লেটোর সাম্যবাদ কী?",
        "answer": "",
        "year": "2nd",
        "exam_year": "2018",
        "sl": "২",
        "section": "খ-বিভাগ",
        "id": "222003_2018_02_02",
        "type": "Board"
    },
    {
        "code": "222003",
        "question": "এরিস্টটলের দাসপ্রথা সম্পর্কে সংক্ষেপে আলোচনা কর।",
        "answer": "",
        "year": "2nd",
        "exam_year": "2018",
        "sl": "৩",
        "section": "খ-বিভাগ",
        "id": "222003_2018_02_03",
        "type": "Board"
    },
    {
        "code": "222003",
        "question": "সেন্ট অগাস্টিনের দৃষ্টিতে পার্থিব রাষ্ট্রের বর্ণনা দাও।",
        "answer": "",
        "year": "2nd",
        "exam_year": "2018",
        "sl": "৪",
        "section": "খ-বিভাগ",
        "id": "222003_2018_02_04",
        "type": "Board"
    },
    {
        "code": "222003",
        "question": "একুইনাসের মতে আইনের শ্রেণীবিভাগ সংক্ষেপে আলোচনা কর।",
        "answer": "",
        "year": "2nd",
        "exam_year": "2018",
        "sl": "৫",
        "section": "খ-বিভাগ",
        "id": "222003_2018_02_05",
        "type": "Board"
    },
    {
        "code": "222003",
        "question": "কৌটিল্যের প্রশাসন ব্যবস্থা সম্পর্কে আলোচনা কর।",
        "answer": "",
        "year": "2nd",
        "exam_year": "2018",
        "sl": "৬",
        "section": "খ-বিভাগ",
        "id": "222003_2018_02_06",
        "type": "Board"
    },
    {
        "code": "222003",
        "question": "ইবনে খালদুনের মতে আসাবিয়া কী?",
        "answer": "",
        "year": "2nd",
        "exam_year": "2018",
        "sl": "৭",
        "section": "খ-বিভাগ",
        "id": "222003_2018_02_07",
        "type": "Board"
    },
    {
        "code": "222003",
        "question": "টমাস হবসের প্রকৃতির রাজ্যের সংক্ষিপ্ত বর্ণনা দাও।",
        "answer": "",
        "year": "2nd",
        "exam_year": "2018",
        "sl": "৮",
        "section": "খ-বিভাগ",
        "id": "222003_2018_02_08",
        "type": "Board"
    },
    {
        "code": "222003",
        "question": "প্রাকৃতিক আইন সম্পর্কে জন লকের ধারণা লিখ।",
        "answer": "",
        "year": "2nd",
        "exam_year": "2018",
        "sl": "৯",
        "section": "খ-বিভাগ",
        "id": "222003_2018_02_09",
        "type": "Board"
    },
    {
        "code": "222003",
        "question": "প্লেটোর আদর্শ রাষ্ট্রের ধারণা ব্যাখ্যা কর।",
        "answer": "",
        "year": "2nd",
        "exam_year": "2018",
        "sl": "১০",
        "section": "গ-বিভাগ",
        "id": "222003_2018_03_10",
        "type": "Board"
    },
    {
        "code": "222003",
        "question": "এরিস্টটলের বিপ্লব তত্ত্ব আলোচনা কর।",
        "answer": "",
        "year": "2nd",
        "exam_year": "2018",
        "sl": "১১",
        "section": "গ-বিভাগ",
        "id": "222003_2018_03_11",
        "type": "Board"
    },
    {
        "code": "222003",
        "question": "সেন্ট টমাস একুইনাসের আইন তত্ত্ব সংক্ষেপে বর্ণনা কর।",
        "answer": "",
        "year": "2nd",
        "exam_year": "2018",
        "sl": "১২",
        "section": "গ-বিভাগ",
        "id": "222003_2018_03_12",
        "type": "Board"
    },
    {
        "code": "222003",
        "question": "সমাজবিজ্ঞানী হিসেবে ইবনে খালদুনের অবদান মূল্যায়ন কর।",
        "answer": "",
        "year": "2nd",
        "exam_year": "2018",
        "sl": "১৩",
        "section": "গ-বিভাগ",
        "id": "222003_2018_03_13",
        "type": "Board"
    },
    {
        "code": "222003",
        "question": "শক্তিশালী জাতিরাষ্ট্র সম্পর্কে ম্যাকিয়াভেলির ধারণা পর্যালোচনা কর।",
        "answer": "",
        "year": "2nd",
        "exam_year": "2018",
        "sl": "১৪",
        "section": "গ-বিভাগ",
        "id": "222003_2018_03_14",
        "type": "Board"
    },
    {
        "code": "222003",
        "question": "সার্বভৌমত্ব সম্পর্কে টমাস হবসের মতবাদ আলোচনা কর।",
        "answer": "",
        "year": "2nd",
        "exam_year": "2018",
        "sl": "১৫",
        "section": "গ-বিভাগ",
        "id": "222003_2018_03_15",
        "type": "Board"
    },
    {
        "code": "222003",
        "question": "জন লকের সম্পত্তি তত্ত্ব ব্যাখ্যা কর।",
        "answer": "",
        "year": "2nd",
        "exam_year": "2018",
        "sl": "১৬",
        "section": "গ-বিভাগ",
        "id": "222003_2018_03_16",
        "type": "Board"
    },
    {
        "code": "222003",
        "question": "রুশোর সামাজিক চুক্তি মতবাদটি পর্যালোচনা কর।",
        "answer": "",
        "year": "2nd",
        "exam_year": "2018",
        "sl": "১৭",
        "section": "গ-বিভাগ",
        "id": "222003_2018_03_17",
        "type": "Board"
    }
]